README.md
setup.py
varr_0/__init__.py
varr_0/see.py
varr_0.egg-info/PKG-INFO
varr_0.egg-info/SOURCES.txt
varr_0.egg-info/dependency_links.txt
varr_0.egg-info/requires.txt
varr_0.egg-info/top_level.txt
varr_0/theory/1.png
varr_0/theory/2.png
varr_0/theory/3.png
varr_0/theory/4.png
varr_0/theory/__init__.py