Metadata-Version: 2.1
Name: varr_0
Version: 0.0.1
Summary: This is the simplest module for quick work with files.
License: MIT
Requires-Dist: IPython
